macops/__init__.py
macops/change.py
macops/generate.py
macops/get.py
macops/reset.py
macops/test.py
macops-3.2.6.dist-info/METADATA
macops-3.2.6.dist-info/WHEEL
macops-3.2.6.dist-info/entry_points.txt
macops-3.2.6.dist-info/top_level.txt
macops-3.2.6.dist-info/RECORD
