Metadata-Version: 2.1
Name: macops
Version: 3.2.6
Summary: It is a python module which can help you to change the current mac address of a certain interface, generate a mac address, get the current mac address and also reset the current mac address to the original one.
Home-page: https://github.com/ShounakKulkarni/MacOps/
Author: Shounak Kulkarni
Author-email: shounak_kulkarni@outlook.com
License: MIT
Platform: UNKNOWN
Classifier: License :: OSI Approved :: MIT License
Classifier: Programming Language :: Python
Classifier: Programming Language :: Python :: 3
Requires-Dist: randmac
Requires-Dist: pathlib
